src/torado_th3knv/__init__.py
src/torado_th3knv/torado.py
torado-0.0.2.dist-info/METADATA
torado-0.0.2.dist-info/WHEEL
torado-0.0.2.dist-info/licenses/LICENSE
torado-0.0.2.dist-info/RECORD
