Metadata-Version: 2.1
Name: torado
Version: 0.0.2
Summary: Routes your traffic through TOR Network
Project-URL: Homepage, https://github.com/th3knv/Torado
Project-URL: Bug Tracker, https://github.com/th3knv/Torado/issues
Author-email: Jok3r <invalid32@protonmail.com>
License-File: LICENSE
Classifier: License :: OSI Approved :: MIT License
Classifier: Operating System :: OS Independent
Classifier: Programming Language :: Python :: 3
Requires-Python: >=3.7
